setup.py
octokit/__init__.py
octokit.egg-info/PKG-INFO
octokit.egg-info/SOURCES.txt
octokit.egg-info/dependency_links.txt
octokit.egg-info/top_level.txt