Metadata-Version: 1.0
Name: octokit
Version: 0.0.1
Summary: Simple Python wrapper for the GitHub API
Home-page: https://github.com/liluo/octokit.py
Author: liluo
Author-email: i@liluo.org
License: MIT License
Keywords: octokit,github,api
Platform: UNKNOWN
